{
  "squad": [
    {
      "value": "1",
      "label": "Data Science"
    },
    {
      "value": "2",
      "label": "Frontend"
    },
    {
      "value": "3",
      "label": "Backend"
    },
    {
      "value": "4",
      "label": "Mobile"
    },
    {
      "value": "5",
      "label": "DevOps"
    },
    {
      "value": "6",
      "label": "Developers"
    },
    {
      "value": "7",
      "label": "Designers"
    },
    {
      "value": "8",
      "label": "QA Engineers"
    }
  ],
  "skills": [
    {
      "value": "1",
      "label": "React Js"
    },
    {
      "value": "2",
      "label": "React Native"
    },
    {
      "value": "3",
      "label": "Angular"
    },
    {
      "value": "4",
      "label": "C#"
    },
    {
      "value": "5",
      "label": "Mobile"
    },
    {
      "value": "6",
      "label": "Javascript"
    },
    {
      "value": "7",
      "label": "CSS3"
    },
    {
      "value": "8",
      "label": "GIT"
    },
    {
      "value": "9",
      "label": "Python"
    },
    {
      "value": "10",
      "label": "R"
    },
    {
      "value": "11",
      "label": "SQL"
    },
    {
      "value": "11",
      "label": "Power BI"
    },
    {
      "value": "12",
      "label": "Selenium"
    },
    {
      "value": "13",
      "label": "Jest"
    },
    {
      "value": "14",
      "label": "Node"
    },
    {
      "value": "15",
      "label": "Figma"
    },
    {
      "value": "16",
      "label": "Sketch"
    },
    {
      "value": "17",
      "label": "Illustrator"
    },
    {
      "value": "17",
      "label": "Photoshop"
    },
    {
      "value": "18",
      "label": "Vue"
    },
    {
      "value": "19",
      "label": "Typescript"
    },
    {
      "value": "20",
      "label": "NextJs"
    },
    {
      "value": "21",
      "label": "Nest JS"
    },
    {
      "value": "22",
      "label": "Java"
    },
    {
      "value": "23",
      "label": " PostgreSQL"
    },
    {
      "value": "24",
      "label": "Flutter"
    },
    {
      "value": "25",
      "label": "AWS"
    },
    {
      "value": "26",
      "label": "Docker"
    }
  ],
  "squadInfo": [
    {
      "id": "1",
      "squadName": "Frontend",
      "squadLeaderName": "Ana Silva",
      "squadMembers": ["Julia Costa", "Gustavo Santos"]
    },
    {
      "id": "2",
      "squadName": "Backend",
      "squadLeaderName": "Lucas Santos",
      "squadMembers": ["Mariana Oliveira", "Pedro Lima", "Gustavo Silva"]
    },
    {
      "id": "3",
      "squadName": "Mobile",
      "squadLeaderName": "Julia Costa",
      "squadMembers": ["Ana Costa", "Lucas Oliveira"]
    },
    {
      "id": "4",
      "squadName": "Data Science",
      "squadLeaderName": "Gustavo Oliveira",
      "squadMembers": ["Mariana Oliveira", "Lucas Costa"]
    },
    {
      "id": "5",
      "squadName": "DevOps",
      "squadLeaderName": "Gustavo Santos",
      "squadMembers": ["Ana Costa", "Julia Santos"]
    },
    {
      "id": "6",
      "squadName": "Developers",
      "squadLeaderName": "Jane Smith",
      "squadMembers": ["Jack Johnson", "Jenny Lee"]
    },
    {
      "id": "7",
      "squadName": "Designers",
      "squadLeaderName": "John Doe",
      "squadMembers": ["Karen Kim", "David Nguyen", "Lena Lee"]
    },
    {
      "id": "8",
      "squadName": "QA Engineers",
      "squadLeaderName": "Sarah Johnson",
      "squadMembers": ["David Kim", "Lena Lee"]
    }
  ],
  "users": [
    {
      "id": 1,
      "imagePath": "https://randomuser.me/api/portraits/men/1.jpg",
      "fullName": "Lucas Oliveira",
      "jobPosition": "Desenvolvedor",
      "squadName": "Frontend",
      "squad": {
        "squadName": "Frontend",
        "squadLeaderName": "Ana Silva",
        "squadMembers": ["Julia Costa", "Gustavo Santos"]
      },
      "hardSkills": [
        {
          "value": "1",
          "label": "React Js"
        },
        {
          "value": "3",
          "label": "Angular"
        },
        {
          "value": "18",
          "label": "Vue"
        },
        {
          "value": "6",
          "label": "Javascript"
        },
        {
          "value": "7",
          "label": "CSS3"
        },
        {
          "value": "19",
          "label": "Typescript"
        },

        {
          "value": "20",
          "label": "NextJs"
        },
        {
          "value": "8",
          "label": "GIT"
        },
        {
          "value": "14",
          "label": "Node"
        }
      ],
      "bio": "Lorem Ipsum is simply dummy text of the printing and typesetting industry. Lorem Ipsum has been the industry's standard dummy text ever since the 1500s, when an unknown printer took a galley of type and scrambled it to make a type specimen book."
    },
    {
      "id": 2,
      "imagePath": "https://randomuser.me/api/portraits/women/2.jpg",
      "fullName": "Ana Costa",
      "jobPosition": "Desenvolvedora",
      "squadName": "Backend",
      "squad": {
        "squadName": "Backend",
        "squadLeaderName": "Lucas Santos",
        "squadMembers": ["Mariana Oliveira", "Pedro Lima", "Gustavo Silva"]
      },
      "hardSkills": [
        {
          "value": "14",
          "label": "Node"
        },
        {
          "value": "21",
          "label": "  Nest JS"
        },
        {
          "value": "22",
          "label": "Java"
        },
        {
          "value": "4",
          "label": "C#"
        },
        {
          "value": "11",
          "label": "SQL"
        },
        {
          "value": "23",
          "label": " PostgreSQL"
        }
      ],
      "bio": "Lorem Ipsum is simply dummy text of the printing and typesetting industry. Lorem Ipsum has been the industry's standard dummy text ever since the 1500s, when an unknown printer took a galley of type and scrambled it to make a type specimen book."
    },
    {
      "id": 3,
      "imagePath": "https://randomuser.me/api/portraits/men/3.jpg",
      "fullName": "Gustavo Silva",
      "jobPosition": "Desenvolvedor",
      "squadName": "Mobile",
      "squad": {
        "squadName": "Mobile",
        "squadLeaderName": "Julia Costa",
        "squadMembers": ["Ana Costa", "Lucas Oliveira"]
      },
      "hardSkills": [
        {
          "value": "2",
          "label": "React Native"
        },
        {
          "value": "24",
          "label": "Flutter"
        },
        {
          "value": "6",
          "label": "Javascript"
        },
        {
          "value": "25",
          "label": "AWS"
        }
      ],
      "bio": "Lorem Ipsum is simply dummy text of the printing and typesetting industry. Lorem Ipsum has been the industry's standard dummy text ever since the 1500s, when an unknown printer took a galley of type and scrambled it to make a type specimen book."
    },
    {
      "id": 4,
      "imagePath": "https://randomuser.me/api/portraits/women/4.jpg",
      "fullName": "Julia Santos",
      "jobPosition": "Desenvolvedora",
      "squadName": "Data Science",
      "squad": {
        "squadName": "Data Science",
        "squadLeaderName": "Gustavo Oliveira",
        "squadMembers": ["Mariana Oliveira", "Lucas Costa"]
      },
      "hardSkills": [  {
        "value": "9",
        "label": "Python"
      },     {
        "value": "10",
        "label": "R"}
      ,   {
        "value": "11",
        "label": "Power BI"
      },   {
        "value": "11",
        "label": "SQL"
      }],
      "bio": "Lorem Ipsum is simply dummy text of the printing and typesetting industry. Lorem Ipsum has been the industry's standard dummy text ever since the 1500s, when an unknown printer took a galley of type and scrambled it to make a type specimen book."
    },
    {
      "id": 5,
      "imagePath": "https://randomuser.me/api/portraits/men/5.jpg",
      "fullName": "Pedro Costa",
      "jobPosition": "Desenvolvedor",
      "squadName": "DevOps",
      "squad": {
        "squadName": "DevOps",
        "squadLeaderName": "Gustavo Santos",
        "squadMembers": ["Ana Costa", "Julia Santos"]
      },
      "hardSkills": [
        {
          "value": "26",
          "label": "Docker"
        },
        {
          "value": "25",
          "label": "AWS"
        },
        {
          "value": "12",
          "label": "Selenium"
        },
        {
          "value": "13",
          "label": "Jest"
        }
      ],
      "bio": "Lorem Ipsum is simply dummy text of the printing and typesetting industry. Lorem Ipsum has been the industry's standard dummy text ever since the 1500s, when an unknown printer took a galley of type and scrambled it to make a type specimen book."
    },
    {
      "id": 6,
      "imagePath": "https://randomuser.me/api/portraits/women/6.jpg",
      "fullName": "Mariana Oliveira",
      "jobPosition": "Desenvolvedora",
      "squadName": "Frontend",
      "squad": {
        "squadName": "Frontend",
        "squadLeaderName": "Lucas Oliveira",
        "squadMembers": ["Pedro Costa", "Gustavo Santos"]
      },
      "hardSkills": [
        {
          "label": "React Js",
          "value": "1"
        },
        {
          "label": "Angular",
          "value": "3"
        },
        {
          "value": "18",
          "label": "Vue"
        },
        {
          "label": "Javascript",
          "value": "6"
        },
        {
          "label": "CSS3",
          "value": "7"
        }
      ],
      "bio": "Lorem Ipsum is simply dummy text of the printing and typesetting industry. Lorem Ipsum has been the industry's standard dummy text ever since the 1500s, when an unknown printer took a galley of type and scrambled it to make a type specimen book."
    },
    {
      "id": 7,
      "imagePath": "https://randomuser.me/api/portraits/women/7.jpg",
      "fullName": "Carolina Oliveira",
      "jobPosition": "Desenvolvedora",
      "squadName": "Backend",
      "squad": {
        "squadName": "Backend",
        "squadLeaderName": "Felipe Almeida",
        "squadMembers": ["Pedro Oliveira", "Marcela Lima"]
      },
      "hardSkills": [
        {
          "value": "22",
          "label": "Java"
        },
        {
          "value": "14",
          "label": "Node"
        },
        {
          "value": "23",
          "label": " PostgreSQL"
        }
      ],
      "bio": "Lorem Ipsum is simply dummy text of the printing and typesetting industry. Lorem Ipsum has been the industry's standard dummy text ever since the 1500s, when an unknown printer took a galley of type and scrambled it to make a type specimen book."
    },
    {
      "id": 8,
      "imagePath": "https://randomuser.me/api/portraits/women/8.jpg",
      "fullName": "Mia Young",
      "jobPosition": "Desenvolvedora",
      "squadName": "Developers",
      "squad": {
        "squadName": "Developers",
        "squadLeaderName": "Jane Smith",
        "squadMembers": ["Jack Johnson", "Jenny Lee"]
      },
      "hardSkills": [
        {
          "label": "React Js",
          "value": "1"
        },
        {
          "label": "Javascript",
          "value": "6"
        },
        {
          "value": "14",
          "label": "Node"
        },
        {
          "label": "CSS3",
          "value": "7"
        },
        {
          "label": "GIT",
          "value": "8"
        }
      ],
      "bio": "Lorem Ipsum is simply dummy text of the printing and typesetting industry. Lorem Ipsum has been the industry's standard dummy text ever since the 1500s, when an unknown printer took a galley of type and scrambled it to make a type specimen book."
    },
    {
      "id": 9,
      "imagePath": "https://randomuser.me/api/portraits/men/10.jpg",
      "fullName": "Eric Hernandez",
      "jobPosition": "Desenvolvedora",
      "squadName": "Designers",
      "squad": {
        "squadName": "Designers",
        "squadLeaderName": "John Doe",
        "squadMembers": ["Karen Kim", "David Nguyen", "Lena Lee"]
      },
      "hardSkills": [
        {
          "value": "15",
          "label": "Figma"
        },
        {
          "value": "16",
          "label": "Sketch"
        },
        {
          "value": "17",
          "label": "Illustrator"
        },
        {
          "value": "17",
          "label": "Photoshop"
        },
        {
          "label": "CSS3",
          "value": "7"
        }
      ],
      "bio": "Lorem Ipsum is simply dummy text of the printing and typesetting industry. Lorem Ipsum has been the industry's standard dummy text ever since the 1500s, when an unknown printer took a galley of type and scrambled it to make a type specimen book."
    },
    {
      "id": 10,
      "imagePath": "https://randomuser.me/api/portraits/women/14.jpg",
      "fullName": "Emily Davis",
      "jobPosition": "Desenvolvedora",
      "squadName": "Developers",
      "squad": {
        "squadName": "Developers",
        "squadLeaderName": "Jane Smith",
        "squadMembers": ["Jack Johnson", "Jenny Lee"]
      },
      "hardSkills": [
        {
          "label": "React Js",
          "value": "1"
        },
        {
          "label": "Javascript",
          "value": "6"
        },
        {
          "value": "14",
          "label": "Node"
        },
        {
          "label": "CSS3",
          "value": "7"
        },
        {
          "label": "GIT",
          "value": "8"
        }
      ],
      "bio": "Lorem Ipsum is simply dummy text of the printing and typesetting industry. Lorem Ipsum has been the industry's standard dummy text ever since the 1500s, when an unknown printer took a galley of type and scrambled it to make a type specimen book."
    },
    {
      "id": 11,
      "imagePath": "https://randomuser.me/api/portraits/men/9.jpg",
      "fullName": "Ryan Thompson",
      "jobPosition": "Desenvolvedor",
      "squadName": "QA Engineers",
      "squad": {
        "squadName": "QA Engineers",
        "squadLeaderName": "Sarah Johnson",
        "squadMembers": ["David Kim", "Lena Lee"]
      },
      "hardSkills": [
        {
          "value": "12",
          "label": "Selenium"
        },
        {
          "value": "13",
          "label": "Jest"
        },
        {
          "value": "14",
          "label": "Node"
        },
        {
          "label": "Javascript",
          "value": "6"
        },
        {
          "label": "GIT",
          "value": "8"
        }
      ],
      "bio": "Lorem Ipsum is simply dummy text of the printing and typesetting industry. Lorem Ipsum has been the industry's standard dummy text ever since the 1500s, when an unknown printer took a galley of type and scrambled it to make a type specimen book."
    },
    {
      "id": 12,
      "imagePath": "https://randomuser.me/api/portraits/women/12.jpg",
      "fullName": "Olivia Wilson",
      "jobPosition": "Desenvolvedora",
      "squadName": "Data Science",
      "squad": {
        "squadName": "Data Science",
        "squadLeaderName": "Emily Smith",
        "squadMembers": ["John Lee", "Karen Kim"]
      },
      "hardSkills": [
        {
          "value": "9",
          "label": "Python"
        },
        {
          "value": "10",
          "label": "R"
        },
        {
          "value": "11",
          "label": "SQL"
        },
        {
          "value": "11",
          "label": "Power BI"
        }
      ],
      "bio": "Lorem Ipsum is simply dummy text of the printing and typesetting industry. Lorem Ipsum has been the industry's standard dummy text ever since the 1500s, when an unknown printer took a galley of type and scrambled it to make a type specimen book."
    },
    {
      "id": 13,
      "imagePath": "https://randomuser.me/api/portraits/men/13.jpg",
      "fullName": "Daniel Rodriguez",
      "jobPosition": "Desenvolvedor",
      "squadName": "Developers",
      "squad": {
        "squadName": "Developers",
        "squadLeaderName": "Jane Smith",
        "squadMembers": ["Jack Johnson", "Jenny Lee"]
      },
      "hardSkills": [
        {
          "label": "React Js",
          "value": "1"
        },
        {
          "label": "Javascript",
          "value": "6"
        },
        {
          "label": "CSS3",
          "value": "7"
        },
        {
          "label": "GIT",
          "value": "8"
        }
      ],
      "bio": "Lorem Ipsum is simply dummy text of the printing and typesetting industry. Lorem Ipsum has been the industry's standard dummy text ever since the 1500s, when an unknown printer took a galley of type and scrambled it to make a type specimen book."
    },
    {
      "fullName": "Tyrion Lannister Macedo",
      "email": "emaildodoguinho@gmail.com",
      "jobPosition": "Teste",
      "hardSkills": [
        {
          "label": "React Js",
          "value": "1"
        },
        {
          "label": "React Native",
          "value": "2"
        },
        {
          "label": "Angular",
          "value": "3"
        },
        {
          "label": "C#",
          "value": "4"
        }
      ],
      "squadName": "Frontend",
      "inactiveUser": false,
      "imagePath": "https://randomuser.me/api/portraits/women/33.jpg",
      "id": 14
    }
  ]
}
